{
  "id": "2021-10-05_regular",
  "meeting_date": "2021-10-05",
  "meeting_type": "regular",
  "meeting_types": [
    "regular"
  ],
  "title": "Conroe ISD Board Meeting — October 5, 2021",
  "date_display": "October 5, 2021",
  "type_display": "Regular Meeting",
  "types_display": [
    "Regular Meeting"
  ],
  "item_count": 0,
  "has_agenda": false,
  "has_notes": true,
  "pdf_filename": null,
  "generated_at": "2026-04-08T02:21:01.690245Z",
  "sections": [],
  "agenda_breakdown_md": "",
  "meeting_notes_md": "# Conroe ISD Board Meeting — 2021-10-05\n*Regular Meeting — Unofficial Notes*\n*Based on auto-generated transcript. Not an official record.*\n*Generated 2026-03-28 14:05 UTC*\n\n---\n\n# Unofficial Meeting Notes\n## Conroe ISD Board Workshop\n### October 5, 2021 | Regular Meeting\n\n---\n\n*These are unofficial notes based on an auto-generated transcript and may contain errors or omissions.*\n\n**Board Members Present:** President Hubert, Mr. Sanders, Mr. Williams, Mr. Inman, and other board members (not all individually identified by name in transcript)\n\n**Board Members Absent:** Mr. Moore (out due to work responsibilities; noted as having exceeded required training hours through TASB work)\n\n**Meeting Duration:** Approximately 7:00 PM – 9:20 PM\n\n---\n\n## Public Comment\n\nNo members of the public signed up to speak.\n\n---\n\n## Item 1: Employee Benefits and Extended Sick Leave Discussion\n\n**Presenters:** Darren Rice and Paula Green (from HR/Benefits)\n\n### Background\n- Extended sick leave (ESL) was adopted by the Board in 1990.\n- Originally, the benefit was paid at **half pay** with a generous leave package (2 local leave days, 5 local sick days, 5 local funeral days).\n- Over time, the benefit was reduced to control costs. It was changed from **half pay** to **half dock** — a critical distinction that causes significant employee confusion.\n- Conroe ISD currently offers only **2 local leave days**, compared to peer districts that offer **5-7 local leave days** with accumulation.\n- Conroe ISD is believed to be the **only district in the state** that offers extended sick leave.\n\n### How Extended Sick Leave Works\n- Available to full-time employees after all other leave is exhausted.\n- Provides up to **30 work days** per school year at **half-dock pay** for personal illness/injury, family illness, birth/adoption of a child.\n- \"Half dock\" means half of the daily rate (annual salary ÷ contract days), **not** half of the employee's standard paycheck — a source of major confusion.\n- The calculation is entirely **manual** — no automated system can handle the variables — creating significant administrative burden not included in the $750K annual cost figure.\n\n### Key Statistics\n- Only **4.4% of employees** (~350 people) use ESL annually.\n- Annual cost: approximately **$750,000** (does not include substitute costs or administrative man-hours).\n- Largest ESL use category: **maternity/adoption**, with average usage of ~19-20 days. A significant number of employees who used ESL for this reason subsequently left the district.\n\n### Peer District Comparison\n- A comparison chart showed peer districts offering 5-7 local leave days with accumulation (rollover) options. Some districts also offer separate paid funeral leave days. Conroe ISD offers neither accumulation nor separate funeral leave.\n\n### Administration's Recommendation\n1. **Discontinue extended sick leave** effective **2023-2024 school year** (allowing a transition period for employees to plan, accumulate days, and purchase disability insurance if desired).\n2. **Continue providing 3 additional local leave days** (approved for COVID-19 leave in 2021) for a **total of 5 local leave days per year**.\n   - Estimated cost: **$1 million/year** (based on all teachers using all 3 additional days), available to **100% of employees**.\n   - Incremental cost over current ESL: approximately **$250,000**.\n3. **Allow employees to carry over (bank) unused local leave days** or be paid at the substitute rate at end of fiscal year. Default would be rollover.\n4. **Pay out accumulated local leave days upon separation** up to a **$5,000 cap** (at substitute rate, currently ~$105/day for certified teachers).\n   - Rationale: Prevents departing employees from burning through banked days unnecessarily; keeps teachers in classrooms.\n\n### Board Discussion & Positions\n- **Multiple board members** asked clarifying questions about the math, the philosophy behind ESL, and the cost implications.\n- **One board member** questioned why the district would increase costs from $750K to $1M and expressed skepticism about the change as a recruiting tool, noting that a pay raise discussion would come in April/May anyway.\n- **Another board member** suggested keeping both ESL and additional local days. Administration explained this would remove the incentive to bank days, as employees would still burn through leave to access ESL.\n- **Dr. Knoll** emphasized the competitive disadvantage of only 2 local days and noted he'd hired ~1,000 people and never had a candidate mention ESL, but had frequent conversations about the low number of local days.\n- **Mr. Inman** stressed the importance of getting **teacher feedback** before making changes.\n- Administration confirmed next steps would include taking the proposal to the **Employee Benefits Committee** and **District Level Planning and Decision Making Committee** for feedback before returning to the Board.\n\n### Important Policy Note\n- Mrs. Gladys noted that at the **November meeting**, the Board would adopt policy DEC, but clarified this relates to legislative session leave changes, **not** this ESL discussion.\n\n**No vote was taken.** This was a discussion/workshop item.\n\n---\n\n## Item 2: Student Support Services Overview\n\n**Presenters:** Dr. Chris Hines (Deputy Superintendent), Dr. Tamika Taylor (Assistant Superintendent for Student Support Services), Jeff Fuller and Hartwell Brown (Directors of School Improvement & Transformational Leadership), Rod Chavez (Director of Dropout Prevention & Recovery), Denise Apollo/Griffin (Coordinator of Student Support Services), Lindsay Taylor (Mental Health Specialist), and Kim Earthman (Director of Student Support Services)\n\n### District Demographics Context (Dr. Hines)\n- District has grown from **37,000 to 67,000 students** since 2003.\n- Current demographics: 43.1% White, 39.6% Hispanic, 9% African American, 4.9% Asian, 3.8% Two or More Races.\n- **17% Limited English Proficient** (80+ languages spoken; estimated 25-30% of families don't speak English at home).\n- **39.6% economically disadvantaged** (up from ~27% in 2003).\n- **172 students in foster care**, **332 homeless students**, **54 migrant family students**, **381 military-connected students**, **1,960 recent immigrants**.\n- **36.2% at-risk**, **9.3% receiving 504 services**, **9.3% receiving special education services**.\n\n### School Improvement & Transformational Leadership (Fuller & Brown)\n\n**Mission:** Develop and promote exceptional leaders for student achievement through coaching.\n\n**Key Activities:**\n- Develop processes, protocols, and systems for campus leaders\n- Build positive culture and climate on campuses\n- Coach on data-driven instruction — shifting from merely discussing data to actively addressing misconceptions and modeling re-teaching strategies\n- Create observation and feedback cycles for principals — moving from summative to formative, small-chunk observations\n\n**Transformational Leadership Pipeline (3 strands):**\n1. **Aspire to Lead (Teacher Leaders):** 108 participants, 5 training sessions/year\n2. **Aspire to Lead (Assistant Principals):** 103-104 participants, 9 sessions\n3. **Aspiring Principals:** 22-23 participants (application process), 8 sessions\n\n**External Partnerships:** IntoLearning (executive leadership), Holdsworth program (leadership pipeline development)\n\n**Board member Mr. Hubert** asked for concrete examples of transformation. Mr. Fuller provided a detailed example of transitioning campuses from data-discussion meetings to data-driven instruction meetings where teachers collaboratively analyze student misconceptions, script re-teaching approaches, and model instruction in real-time.\n\n### Dropout Prevention & Recovery (Mr. Chavez)\n\n**Key Statistics:**\n- **Attendance rate:** 96.3% vs. state average (pre-pandemic 2018-19 data)\n- **Cohort graduation rate:** 95.3-96.4% vs. state's 90%\n- **Dropout rate:** 0.9% vs. state's 5.7-5.9%\n- **Annual dropout rate:** 0.2% vs. state's 1.9%\n\n**Primary reasons for dropouts:** Economic — students needing to work to support families, exacerbated by the pandemic.\n\n**Key point:** Once a student drops out, they cannot be counted as a dropout twice, creating an incentive for the district to continue pursuing them. Students have up to 6 years to complete graduation.\n\n**Department staffing:** Presented as a team chart showing positions funded through a patchwork of **local funds, state compensatory funds, special education funds, ESSER money, homeless grants, Title I, Title III, Medicaid funds**, and other grants.\n\n**Board member concern (Mr. Williams):** Expressed significant concern about reliance on grant funding for essential student support services, particularly as ESSER funds will expire. Urged the district to budget these positions more sustainably. Dr. Knoll acknowledged a transition plan is being developed to move ESSER-funded positions into the regular budget as enrollment growth provides additional funding.\n\n**Programs Highlighted:**\n- **Project Mentor:** 200 mentors paired with 200 mentees; mentors commit to one lunch visit per week. Managed by 1.6 FTE. Dr. Knoll's father (Michael Noll) cited as a long-time dedicated mentor. Board members discussed the program's value and limitations. **Open to community volunteers** — Angela Matthews conducts outreach to churches and civic organizations.\n- **Communities in Schools (CIS):** 20 contracted positions across the district. Provide mini-counseling, resource connection, food distribution. Partially grant-funded, partially locally funded. Cost-effective program. CIS workers are contracted employees, not on CISD payroll/benefits.\n- **Proposity App:** Allows community members to see specific family needs (jackets, shoes, etc.) and purchase items delivered directly via Amazon.\n- **Parent & Family Engagement Liaisons:** 13 parent liaisons and 4 family engagement liaisons hired by principals. Some funded by ESSER III and Title funds.\n- **Community Partnerships:** Lone Star Family Health Center (medical, dental, vaccinations, mental health), Lone Star College, Woodforest Bank, Montgomery County Food Bank, Tri-County Behavioral Health Center.\n\n**Hispanic Achievement Celebration:** 20th annual event scheduled for April 21st at the new jet center behind Woodforest Stadium.\n\n### Guidance & Counseling (Denise Apollo/Griffin)\n\n**Staffing:** **173 school counselors** — an increase of 15 from the prior year.\n\n**Key Functions (per Texas Education Code 38.351):**\n- Early mental health prevention and intervention\n- Substance abuse prevention\n- Suicide prevention, intervention, and postvention\n- Grief-informed and trauma-informed practices\n- Positive behavior interventions and supports (PBIS)\n- Positive youth development\n- Building skills for managing emotions, relationships, and decision-making\n\n**Employee Assistance Program (EAP):** Support Link — free, confidential support available 24/7/365 for all staff and household members up to age 26, regardless of district insurance enrollment. Includes counseling, legal, financial, wellness, and other resources.\n\n**Community Health Partnerships:**\n- **Tri-County Behavioral Health:** On-campus mental health services at 4 school sites; served 3,600 student contacts in 2020-21. Operates at ~$50,000 loss per site per year.\n- **YES to Youth Montgomery County:** Provides therapeutic support groups on campuses.\n- **Lone Star Family Health Center:** Medical, dental, mental health services.\n- **T-CHAT (Texas Child Health Access Through Telemental Health):** Telemental health through Senate Bill 11 and the Texas Child Mental Health Care Consortium. Partnership with Baylor College of Medicine. Provides near-immediate psychiatric/psychological appointments versus weeks-long waiting lists. Three laptop computers being deployed to **Conroe High, Caney Creek High, and Oak Ridge High** for on-site telemental health labs. All students district-wide can access T-CHAT; approximately 50 students have used it in the past 2 years.\n\n**Counselor Time Study:** Random 3-day time study confirmed counselors spend well over 80% of their time on direct student counseling activities, meeting the 87th Legislature's requirements (SB counselor duty requirements). Testing coordinator positions had already been put in place to free counselors from testing administration duties.\n\n**Current Challenges:**\n- More suicide outcries reported **at much younger ages**\n- Sharp increase in anxiety and stress\n- **Alarming number of parents who are afraid of their children** (particularly young children; parents calling counselors for help)\n- Severe financial needs of families\n- Sharp rise in grief due to family member deaths\n- CPS reporting is up\n\n**Community Support Highlighted:**\n- Student-created organizations: **Matthew's Birthday Wish** (weekly food support, first aid/hygiene kits), **Ashley's Closet** (clothing/formal wear), **Be Blessed by Bailey Cohert** (backpacks, school supplies, shoes)\n- Churches redirecting mission projects to local community support\n- Area organizations adopting campuses\n\n### Student Support Services / MTSS / PBIS / Social Emotional Learning (Kim Earthman)\n\n**Team:** 14 district-level instructional coaches (12 for campuses, 2 for foster care population), 51.5 campus-based instructional behavior coaches, PBIS liaisons, academic interventionists.\n\n**Foundations (School-Wide PBIS):**\n- 8-year implementation; **all campuses** have now completed training.\n- Based on **Safe and Civil Schools** (Dr. Randy Sprick's research-based framework).\n- Focuses on: clear expectations, consistent structures, positive relationships, school connectedness.\n- **\"Power of Being Seen\"** exercise: Staff mark rosters to identify which students they know by name, personally, academically, and by interests — revealing students with no adult connections. Mr. Brown described implementing this at Washington with follow-up teacher engagement.\n\n**Classroom Management:**\n- Framework-based approach (not one-size-fits-all program)\n- Part of new teacher onboarding (full day of training)\n- District coaches provide ongoing support and classroom observations\n- Focuses on: clear expectations, consistent implementation, positive student-teacher relationships\n\n**Response to Intervention (RTI):**\n- Three-tier model: Tier 1 (all students), Tier 2 (targeted small group), Tier 3 (intensive intervention)\n- **Branching Minds** platform implemented for tracking whole-child progress\n- House Bill 4545 compliance for learning loss addressed collaboratively with Teaching & Learning department\n\n### Social Emotional Learning (SEL) — Significant Board Discussion\n\n**Ms. Earthman** presented Conroe ISD's approach to SEL, emphasizing:\n- All SEL work is **grounded in state law** (Texas Education Code), commissioner's rules, and board policy\n- Handouts provided showing legal citations for every component\n- District developed its own framework through a committee of ~75 teachers, administrators, counselors, and coaches over approximately two years\n- **\"I Can\" statements** developed as curriculum aligned to legal requirements\n- **Not yet fully implemented** — still going back to **SHAC (School Health Advisory Council)** for additional feedback\n\n**What SEL IS in Conroe ISD:**\n- Helping students build skills for managing emotions, positive relationships, and responsible decision-making\n- Using teachable moments for respect, responsibility, trustworthiness, caring, citizenship\n- Explicit instruction in skills some students lack\n- Collaboration with home values\n- Required by state law, TEC, board policy, comprehensive guidance model, commissioner's rules\n\n**What SEL is NOT in Conroe ISD:**\n- Not proselytizing or indoctrinating regarding specific religious or political beliefs (per HB 1026)\n- Not pushing personal beliefs on students\n- Not critical race theory (CRT)\n- Not a replacement for values taught at home\n\n### Significant Board Discussion on SEL, CRT, and Classroom Content\n\n**President Hubert** expressed concern about the confusion between SEL and CRT in public discourse, noting he had never heard of CRT until community members raised it at board meetings. He expressed support for SEL as implemented but wanted clear differentiation.\n\n**Board Member (unnamed, but described as raising concerns about specific incidents)** expressed significant concerns including:\n- Fear that SEL frameworks could be used as vehicles for inappropriate content\n- Referenced specific incidents: a Pixar video shown without preview that contained inappropriate content, a 7th-grade parent complaint about questions regarding LGBTQ friends, a book in a 3rd-grade classroom, and referenced teachers in neighboring districts (Magnolia, Willis, Montgomery) openly stating they would teach CRT regardless of the law\n- Called for stronger **culture of accountability** to prevent such incidents\n- Expressed concern that incidents \"keep slipping through\"\n\n**Mr. Williams** strongly pushed back, arguing:\n- Isolated incidents should not be extrapolated to indict the entire system\n- With 8,500 employees and 68,000 students, mistakes will occur due to volume\n- The district has clearly and repeatedly stated it does not teach CRT\n- Characterized some community complaints as \"conspiracy theories\" and \"fanatic\" approaches\n- Questioned why the board continues to entertain claims that contradict the district's documented practices\n- Stated the board's role is to hire the right superintendent, provide resources, and step back from day-to-day operations\n\n**Dr. Knoll** responded:\n- In every specific incident raised, there has been accountability\n- The Pixar video incident: teacher selected from a complete list of Pixar movies without previewing; principal called every parent that night; fully addressed\n- The 7th-grade incident: investigation revealed a counselor conducting a Naviance four-year planning survey asked \"Do you like to be around people that are different from you?\" — not an LGBTQ-specific question as characterized by the parent\n- Emphasized the district reflects community values\n- Acknowledged mistakes will happen with millions of instructional minutes daily but are addressed when identified\n- Stated he does not believe there is a systemic culture problem\n\n**Ms. Earthman** confirmed that the SEL framework has not yet been rolled out to all teachers; it was shared with administrators and counselors. Professional learning for teachers is planned. The SHAC committee (School Health Advisory Council — composed of parents, school staff, community members, and students) will provide additional feedback.\n\n**Process for vetting instructional materials** was discussed:\n- **Required curriculum:** Vetted through textbook selection committees, open to public\n- **Library materials:** Less stringent but subject to formal challenge process per board policy, with ultimate appeal to the Board\n- **Classroom resources:** New teacher training includes Conroe ISD expectations and community values\n\n---\n\n## Closing Remarks\n\n- Dr. Taylor and the student support services teams received praise from multiple board members.\n- **Mr. Sanders** publicly thanked Dr. Taylor for her dedication, citing her personal phone calls inviting him to participate in Read for a Better Life.\n- **Mr. Williams** echoed the sentiment, expressing 20 years of knowing Dr. Taylor and her impact at every level.\n- **Mr. Inman** expressed gratitude for the staff's passion and work.\n- Dr. Knoll thanked the teams for their presentations.\n\n---\n\n## Meeting Adjourned\n\n**Time:** 9:20 PM\n\n---\n\n## Summary of Key Outcomes\n\n| Item | Status |\n|------|--------|\n| Extended Sick Leave reform | **Discussion only; no vote.** Administration recommended discontinuing ESL effective 2023-24 and adding 3 permanent local leave days (total 5) with rollover/banking option. Will go to Employee Benefits Committee and DLPDM Committee for feedback before returning to Board. |\n| Student Support Services presentations | **Informational only.** Multiple departments presented overviews of programs and services. |\n| SEL framework | **Not yet fully implemented.** Going back to SHAC for additional feedback. Professional learning for teachers planned. |\n| CRT/classroom content concerns | **Discussed at length.** Board members expressed differing views on scope of concern. Administration reiterated accountability processes are in place. No action item. |\n\n---\n\n*Note: These are unofficial meeting notes based on an auto-generated transcript. They may contain inaccuracies. For official records, please consult the district's approved meeting minutes.*"
}